Topsis_Devkaran_Singh_102303262/__init__.py
Topsis_Devkaran_Singh_102303262/topsis.py
topsis_devkaran_singh_102303262-0.1.dist-info/licenses/LICENSE.txt
topsis_devkaran_singh_102303262-0.1.dist-info/METADATA
topsis_devkaran_singh_102303262-0.1.dist-info/WHEEL
topsis_devkaran_singh_102303262-0.1.dist-info/top_level.txt
topsis_devkaran_singh_102303262-0.1.dist-info/RECORD
