Metadata-Version: 2.4
Name: Topsis_Devkaran_Singh_102303262
Version: 0.1
Summary: A Topsis Report Generator
Author: Devkaran Singh
Author-email: dsingh7_be23@thapar.edu
Classifier: Programming Language :: Python :: 3
Classifier: License :: OSI Approved :: MIT License
Classifier: Operating System :: OS Independent
License-File: LICENSE.txt
Dynamic: author
Dynamic: author-email
Dynamic: classifier
Dynamic: license-file
Dynamic: summary
